pkgkit/__init__.py
pkgkit/shkit/__init__.py
pkgkit/shkit/runShell.py
pkgkit-0.0.6.dist-info/METADATA
pkgkit-0.0.6.dist-info/RECORD
pkgkit-0.0.6.dist-info/WHEEL
pkgkit-0.0.6.dist-info/top_level.txt
