Metadata-Version: 2.1
Name: pkgkit
Version: 0.0.6
Summary: A pakage toolkit
Home-page: https://github.com/yingHH/easyShell
Author: Ying Huang
Author-email: hhhyyy1992117@qq.com
License: UNKNOWN
Platform: UNKNOWN
Classifier: Programming Language :: Python :: 3.6
Classifier: License :: OSI Approved :: GNU General Public License v3 (GPLv3)
Classifier: Operating System :: POSIX :: Linux
